YD2SG/__init__.py
YD2SG/__main__.py
YD2SG/check_input.py
YD2SG/print_utils.py
YD2SG/timestamping.py
YD2SG/templates/schedule_template.j2
yd2sg-0.1.0.dist-info/METADATA
yd2sg-0.1.0.dist-info/WHEEL
yd2sg-0.1.0.dist-info/entry_points.txt
yd2sg-0.1.0.dist-info/licenses/LICENSE
yd2sg-0.1.0.dist-info/RECORD
