Metadata-Version: 2.1
Name: YD2SG
Version: 0.1.0
Summary: Ylaan's Discord Streaming Schedule Generator
Project-URL: Homepage, https://github.com/Ylaaan/YD2SG
Project-URL: Issues, https://github.com/Ylaaan/YD2SG/issues
Author-email: Ylaan <watsoncholmes@gmail.com>
License-File: LICENSE
Keywords: Discord,Schedule,Template,Ylaan
Classifier: Environment :: Console
Classifier: License :: OSI Approved :: MIT License
Classifier: Operating System :: OS Independent
Classifier: Programming Language :: Python :: 3
Requires-Python: >=3.12
Requires-Dist: jinja2
